{
  "predictions": [
    {
      "id": "pred_20250524T222048593673",
      "prediction": "down",
      "timestamp": "2025-05-24T22:20:48.593673",
      "latest_price": 45800.0,
      "data_points": 30,
      "analysis_period": "2024-01-01 to 2024-01-30"
    },
    {
      "id": "pred_20250524T230326028151",
      "prediction": "down",
      "timestamp": "2025-05-24T23:03:26.028151",
      "latest_price": 45800.0,
      "data_points": 30,
      "analysis_period": "2024-01-01 to 2024-01-30"
    },
    {
      "id": "pred_20250524T233855898029",
      "prediction": "down",
      "timestamp": "2025-05-24T23:38:55.898029",
      "latest_price": 45800.0,
      "data_points": 30,
      "analysis_period": "2024-01-01 to 2024-01-30"
    },
    {
      "id": "pred_20250524T233928889471",
      "prediction": "down",
      "timestamp": "2025-05-24T23:39:28.889471",
      "latest_price": 45800.0,
      "data_points": 30,
      "analysis_period": "2024-01-01 to 2024-01-30"
    },
    {
      "id": "pred_20250524T233945307793",
      "prediction": "down",
      "timestamp": "2025-05-24T23:39:45.307793",
      "latest_price": 45800.0,
      "data_points": 30,
      "analysis_period": "2024-01-01 to 2024-01-30"
    },
    {
      "id": "pred_20250525T000057562456",
      "prediction": "down",
      "timestamp": "2025-05-25T00:00:57.562456",
      "latest_price": 45800.0,
      "data_points": 30,
      "analysis_period": "2024-01-01 to 2024-01-30",
      "confidence": 0.8999999999999999,
      "actual_outcome": null,
      "actual_price": null,
      "evaluation_timestamp": null,
      "success": null
    },
    {
      "id": "pred_20250525T000101863054",
      "prediction": "down",
      "timestamp": "2025-05-25T00:01:01.863054",
      "latest_price": 45800.0,
      "data_points": 30,
      "analysis_period": "2024-01-01 to 2024-01-30",
      "confidence": 0.8999999999999999,
      "actual_outcome": null,
      "actual_price": null,
      "evaluation_timestamp": null,
      "success": null
    },
    {
      "id": "pred_20250525T004235470060",
      "prediction": "down",
      "timestamp": "2025-05-25T00:42:35.470060",
      "latest_price": 45800.0,
      "data_points": 30,
      "analysis_period": "2024-01-01 to 2024-01-30",
      "confidence": 0.8999999999999999,
      "actual_outcome": null,
      "actual_price": null,
      "evaluation_timestamp": null,
      "success": null
    },
    {
      "id": "pred_20250525T004239956817",
      "prediction": "down",
      "timestamp": "2025-05-25T00:42:39.956817",
      "latest_price": 45800.0,
      "data_points": 30,
      "analysis_period": "2024-01-01 to 2024-01-30",
      "confidence": 0.8999999999999999,
      "actual_outcome": null,
      "actual_price": null,
      "evaluation_timestamp": null,
      "success": null
    },
    {
      "id": "pred_20250525T004244472482",
      "prediction": "down",
      "timestamp": "2025-05-25T00:42:44.472482",
      "latest_price": 45800.0,
      "data_points": 30,
      "analysis_period": "2024-01-01 to 2024-01-30",
      "confidence": 0.8999999999999999,
      "actual_outcome": null,
      "actual_price": null,
      "evaluation_timestamp": null,
      "success": null
    },
    {
      "id": "pred_20250525T004300254877",
      "prediction": "down",
      "timestamp": "2025-05-25T00:43:00.254877",
      "latest_price": 45800.0,
      "data_points": 30,
      "analysis_period": "2024-01-01 to 2024-01-30",
      "confidence": 0.8999999999999999,
      "actual_outcome": null,
      "actual_price": null,
      "evaluation_timestamp": null,
      "success": null
    },
    {
      "id": "pred_20250525T005751017133",
      "prediction": "down",
      "timestamp": "2025-05-25T00:57:51.017133",
      "latest_price": 45800.0,
      "data_points": 30,
      "analysis_period": "2024-01-01 to 2024-01-30",
      "confidence": 0.8999999999999999,
      "actual_outcome": null,
      "actual_price": null,
      "evaluation_timestamp": null,
      "success": null
    },
    {
      "id": "pred_20250525T005835240264",
      "prediction": "down",
      "timestamp": "2025-05-25T00:58:35.240264",
      "latest_price": 45800.0,
      "data_points": 30,
      "analysis_period": "2024-01-01 to 2024-01-30",
      "confidence": 0.8999999999999999,
      "actual_outcome": null,
      "actual_price": null,
      "evaluation_timestamp": null,
      "success": null
    },
    {
      "id": "pred_20250525T010212364745",
      "prediction": "down",
      "timestamp": "2025-05-25T01:02:12.364745",
      "latest_price": 45800.0,
      "data_points": 30,
      "analysis_period": "2024-01-01 to 2024-01-30",
      "confidence": 0.8999999999999999,
      "actual_outcome": null,
      "actual_price": null,
      "evaluation_timestamp": null,
      "success": null
    },
    {
      "id": "pred_20250525T010217145672",
      "prediction": "down",
      "timestamp": "2025-05-25T01:02:17.145672",
      "latest_price": 45800.0,
      "data_points": 30,
      "analysis_period": "2024-01-01 to 2024-01-30",
      "confidence": 0.8999999999999999,
      "actual_outcome": null,
      "actual_price": null,
      "evaluation_timestamp": null,
      "success": null
    },
    {
      "id": "pred_20250525T010221699296",
      "prediction": "down",
      "timestamp": "2025-05-25T01:02:21.699296",
      "latest_price": 45800.0,
      "data_points": 30,
      "analysis_period": "2024-01-01 to 2024-01-30",
      "confidence": 0.8999999999999999,
      "actual_outcome": null,
      "actual_price": null,
      "evaluation_timestamp": null,
      "success": null
    },
    {
      "id": "pred_20250525T010823858833",
      "prediction": "down",
      "timestamp": "2025-05-25T01:08:23.858833",
      "latest_price": 45800.0,
      "data_points": 30,
      "analysis_period": "2024-01-01 to 2024-01-30",
      "confidence": 0.8999999999999999,
      "actual_outcome": null,
      "actual_price": null,
      "evaluation_timestamp": null,
      "success": null
    },
    {
      "id": "pred_20250525T010827542942",
      "prediction": "down",
      "timestamp": "2025-05-25T01:08:27.542942",
      "latest_price": 45800.0,
      "data_points": 30,
      "analysis_period": "2024-01-01 to 2024-01-30",
      "confidence": 0.8999999999999999,
      "actual_outcome": null,
      "actual_price": null,
      "evaluation_timestamp": null,
      "success": null
    },
    {
      "id": "pred_20250525T010831421493",
      "prediction": "down",
      "timestamp": "2025-05-25T01:08:31.421493",
      "latest_price": 45800.0,
      "data_points": 30,
      "analysis_period": "2024-01-01 to 2024-01-30",
      "confidence": 0.8999999999999999,
      "actual_outcome": null,
      "actual_price": null,
      "evaluation_timestamp": null,
      "success": null
    },
    {
      "id": "pred_20250525T010911793474",
      "prediction": "down",
      "timestamp": "2025-05-25T01:09:11.793474",
      "latest_price": 45800.0,
      "data_points": 30,
      "analysis_period": "2024-01-01 to 2024-01-30",
      "confidence": 0.8999999999999999,
      "actual_outcome": null,
      "actual_price": null,
      "evaluation_timestamp": null,
      "success": null
    },
    {
      "id": "pred_20250525T012049757915",
      "prediction": "down",
      "timestamp": "2025-05-25T01:20:49.757915",
      "latest_price": 45800.0,
      "data_points": 30,
      "analysis_period": "2024-01-01 to 2024-01-30",
      "confidence": 0.8999999999999999,
      "actual_outcome": null,
      "actual_price": null,
      "evaluation_timestamp": null,
      "success": null
    },
    {
      "id": "pred_20250525T013232734234",
      "prediction": "down",
      "timestamp": "2025-05-25T01:32:32.734234",
      "latest_price": 45800.0,
      "data_points": 30,
      "analysis_period": "2024-01-01 to 2024-01-30",
      "confidence": 0.8999999999999999,
      "actual_outcome": null,
      "actual_price": null,
      "evaluation_timestamp": null,
      "success": null
    }
  ],
  "metadata": {
    "created": "2024-12-28",
    "version": "1.0",
    "description": "Bitcoin price prediction log for autonomous agent"
  }
}